setup.py
quizler/__init__.py
quizler/lib.py
quizler/main.py
quizler/models.py
quizler/utils.py
quizler.egg-info/PKG-INFO
quizler.egg-info/SOURCES.txt
quizler.egg-info/dependency_links.txt
quizler.egg-info/entry_points.txt
quizler.egg-info/requires.txt
quizler.egg-info/top_level.txt
tests/quizler/__init__.py
tests/quizler/test_lib.py
tests/quizler/test_main.py
tests/quizler/test_models.py
tests/quizler/test_utils.py