Metadata-Version: 1.1
Name: quizler
Version: 0.0.6
Summary: Set of utils for Quizlet API
Home-page: https://github.com/quizl/quizler
Author: Pavel Karateev
Author-email: karateev.pavel@ya.ru
License: UNKNOWN
Download-URL: https://github.com/quizl/quizler/archive/0.0.6.tar.gz
Keywords: quizlet,api
Platform: UNKNOWN
